<annotations><filename>image165.png</filename><id>165</id><size><width>720</width><height>720</height><depth>3</depth></size><object><name>fence_breach</name><bndbox><xmin>569</xmin><ymin>603</ymin><xmax>680</xmax><ymax>710</ymax></bndbox></object><object><name>fence_breach</name><bndbox><xmin>307</xmin><ymin>469</ymin><xmax>413</xmax><ymax>577</ymax></bndbox></object><object><name>fence_breach</name><bndbox><xmin>39</xmin><ymin>602</ymin><xmax>151</xmax><ymax>713</ymax></bndbox></object></annotations>